python_example_wierdre.cp313-win_amd64.pyd
python_example_wierdre-0.1.0.dist-info/METADATA
python_example_wierdre-0.1.0.dist-info/WHEEL
python_example_wierdre-0.1.0.dist-info/top_level.txt
python_example_wierdre-0.1.0.dist-info/RECORD
